Metadata-Version: 1.0
Name: bk-distributions
Version: 0.1
Summary: Statistical distributions
Home-page: UNKNOWN
Author: UNKNOWN
Author-email: UNKNOWN
License: UNKNOWN
Platform: UNKNOWN
